{
    "30010943": {
        "input": {
            "fusion": {
                "configuration": {
                    "ip": "10.180.69.189",
                    "port": 30020
                },
                "type": "LOCAL_NETWORK"
            },
            "zed": {
                "configuration": "0",
                "type": ""
            }
        },
        "world": {
            "rotation": [
                0.0,
                0.0,
                0.0
            ],
            "translation": [
                0.0,
                0.0,
                0.0
            ]
        }
    },
    "31230555": {
        "input": {
            "fusion": {
                "configuration": {
                    "ip": "10.180.69.199",
                    "port": 30020
                },
                "type": "LOCAL_NETWORK"
            },
            "zed": {
                "configuration": "0",
                "type": ""
            }
        },
        "world": {
            "rotation": [
                0.0,
                0.0,
                0.0
            ],
            "translation": [
                0.0,
                -2.25307559967041,
                0.0
            ]
        }
    },
    "31924562": {
        "input": {
            "fusion": {
                "configuration": {
                    "ip": "10.180.69.204",
                    "port": 30020
                },
                "type": "LOCAL_NETWORK"
            },
            "zed": {
                "configuration": "0",
                "type": ""
            }
        },
        "world": {
            "rotation": [
                0.013365103863179684,
                -2.4587082862854004,
                0.06380262970924377
            ],
            "translation": [
                1.3433845043182373,
                -2.182906150817871,
                7.938285827636719
            ]
        }
    },
    "34625868": {
        "input": {
            "fusion": {
                "configuration": {
                    "ip": "10.180.69.83",
                    "port": 30020
                },
                "type": "LOCAL_NETWORK"
            },
            "zed": {
                "configuration": "0",
                "type": ""
            }
        },
        "world": {
            "rotation": [
                -0.018256235867738724,
                1.6504333019256592,
                -0.013112081214785576
            ],
            "translation": [
                -6.260857105255127,
                -2.3431317806243896,
                5.606845378875732
            ]
        }
    },
    "38179175": {
        "input": {
            "fusion": {
                "configuration": {
                    "ip": "10.180.69.201",
                    "port": 30020
                },
                "type": "LOCAL_NETWORK"
            },
            "zed": {
                "configuration": "0",
                "type": ""
            }
        },
        "world": {
            "rotation": [
                -0.01144351251423359,
                0.6957578659057617,
                0.007276384625583887
            ],
            "translation": [
                -3.06217622756958,
                -2.3105995655059814,
                2.586733818054199
            ]
        }
    },
    "39779696": {
        "input": {
            "fusion": {
                "configuration": {
                    "ip": "10.180.69.191",
                    "port": 30020
                },
                "type": "LOCAL_NETWORK"
            },
            "zed": {
                "configuration": "0",
                "type": ""
            }
        },
        "world": {
            "rotation": [
                -0.010129502043128014,
                3.1142148971557617,
                -0.02277531661093235
            ],
            "translation": [
                -1.9001201391220093,
                -2.2489778995513916,
                10.651899337768555
            ]
        }
    }
}
